zoommap_converter/__init__.py
zoommap_converter/__main__.py
zoommap_converter/app.py
zoommap_converter/cli.py
zoommap_converter/logs.py
zoommap_converter/bootstrap/loader.py
zoommap_converter/bootstrap/svg.py
zoommap_converter/conf/settings.py
zoommap_converter/converter/converter.py
zoommap_converter/converter/parser.py
zoommap_converter/converter/render.py
zoommap_converter/converter/scraper.py
zoommap_converter/converter/utils.py
zoommap_converter/models/defaults.py
zoommap_converter/models/leaflet.py
zoommap_converter/models/models.py
zoommap_converter/models/zoommap.py
zoommap_converter-0.1.1.dist-info/licenses/LICENSE
zoommap_converter-0.1.1.dist-info/METADATA
zoommap_converter-0.1.1.dist-info/WHEEL
zoommap_converter-0.1.1.dist-info/entry_points.txt
zoommap_converter-0.1.1.dist-info/top_level.txt
zoommap_converter-0.1.1.dist-info/RECORD
