Metadata-Version: 2.4
Name: zoommap-converter
Version: 0.1.1
Summary: A Python CLI tool for converting Leaflet to Zoommap.
Requires-Python: <4.0,>=3.12
License-File: LICENSE
Requires-Dist: obsidianmd-parser>=0.4.0
Requires-Dist: pillow>=12.1.0
Requires-Dist: pydantic>=2.12.5
Dynamic: license-file
